{
  "generated_at": "2026-04-20T18:16:57.011170+00:00",
  "total_branches": 229,
  "by_amendment": {
    "Rust/WASM": 5,
    "Confidential Transfers": 2,
    "Other": 140,
    "OpenTelemetry": 10,
    "Lending": 25,
    "Multi-Purpose Tokens": 3,
    "Smart Escrow": 2,
    "Escrow": 2,
    "Checks": 2,
    "Batch Transactions": 2,
    "Clawback": 1,
    "Testing & CI": 30,
    "Credentials": 1,
    "AMM": 1,
    "Code Modularization": 3
  },
  "by_type": {
    "Feature": 66,
    "CI/CD": 27,
    "Documentation": 11,
    "Bug Fix": 41,
    "Refactor": 31,
    "Testing": 40,
    "Unknown": 13
  },
  "by_source": {
    "ai_kimi": 177,
    "keyword_match": 38,
    "fallback": 13
  }
}