{
  "generated_at": "2026-07-22T19:08:07.149798+00:00",
  "total_branches": 243,
  "by_amendment": {
    "Other": 152,
    "Lending": 21,
    "Multi-Purpose Tokens": 12,
    "OpenTelemetry": 10,
    "Rust/WASM": 6,
    "Batch Transactions": 4,
    "Escrow": 6,
    "Smart Escrow": 2,
    "AMM": 3,
    "Confidential Transfers": 2,
    "Checks": 2,
    "Testing & CI": 20,
    "Credentials": 2,
    "Clawback": 1
  },
  "by_type": {
    "Testing": 34,
    "Unknown": 36,
    "CI/CD": 24,
    "Feature": 79,
    "Refactor": 27,
    "Documentation": 13,
    "Bug Fix": 30
  },
  "by_source": {
    "ai_kimi": 122,
    "keyword_match": 84,
    "fallback": 36
  }
}